oneargopy/OneArgo.py
oneargopy/OneArgoSettings.py
oneargopy/__init__.py
oneargopy-0.1.7.dist-info/licenses/LICENSE
tests/test_oneargopy.py
oneargopy-0.1.7.dist-info/METADATA
oneargopy-0.1.7.dist-info/WHEEL
oneargopy-0.1.7.dist-info/top_level.txt
oneargopy-0.1.7.dist-info/RECORD
